firecrest/Authorization.py
firecrest/FirecrestException.py
firecrest/__init__.py
firecrest/cli_script.py
firecrest/path.py
firecrest/py.typed
firecrest/types.py
firecrest/utilities.py
firecrest/cli/__init__.py
firecrest/cli2/__init__.py
firecrest/v1/AsyncClient.py
firecrest/v1/AsyncExternalStorage.py
firecrest/v1/BasicClient.py
firecrest/v1/ExternalStorage.py
firecrest/v1/__init__.py
firecrest/v2/__init__.py
firecrest/v2/_async/Client.py
firecrest/v2/_async/__init__.py
firecrest/v2/_sync/Client.py
pyfirecrest-3.5.0.dist-info/entry_points.txt
pyfirecrest-3.5.0.dist-info/licenses/LICENSE
pyfirecrest-3.5.0.dist-info/WHEEL
pyfirecrest-3.5.0.dist-info/METADATA
pyfirecrest-3.5.0.dist-info/RECORD
