Metadata-Version: 2.4
Name: pyfirecrest
Version: 3.5.0
Summary: pyFirecrest is a python wrapper for FirecREST
Author: CSCS Swiss National Supercomputing Center
Maintainer-email: Eirini Koutsaniti <eirini.koutsaniti@cscs.ch>, Juan Pablo Dorsch <juanpablo.dorsch@cscs.ch>
Requires-Python: >=3.7
Classifier: Programming Language :: Python :: 3.7
Classifier: Programming Language :: Python :: 3.8
Classifier: Programming Language :: Python :: 3.9
Classifier: License :: OSI Approved :: BSD License
Classifier: Operating System :: OS Independent
License-File: LICENSE
Requires-Dist: aiofiles>=23.2.1
Requires-Dist: requests>=2.14.0
Requires-Dist: PyJWT>=2.4.0
Requires-Dist: typer[all]>=0.7.0,<1.0.0
Requires-Dist: packaging>=21.0
Requires-Dist: httpx>=0.24.0
Requires-Dist: PyYAML>=5.1
Requires-Dist: unasync ; extra == "dev"
Requires-Dist: sphinx>=4.0 ; extra == "docs"
Requires-Dist: sphinx-rtd-theme>=1.0 ; extra == "docs"
Requires-Dist: myst-parser>=0.16 ; extra == "docs"
Requires-Dist: sphinx-autobuild>=2021.0 ; extra == "docs"
Requires-Dist: sphinx-click==3.0.2 ; extra == "docs"
Requires-Dist: pytest>=5.3 ; extra == "test"
Requires-Dist: mypy~=0.991 ; extra == "test"
Requires-Dist: types-aiofiles~=23.2.0.0 ; extra == "test"
Requires-Dist: types-requests~=2.28.11 ; extra == "test"
Requires-Dist: pytest-httpserver~=1.0.6 ; extra == "test"
Requires-Dist: pytest-asyncio>=0.21.1 ; extra == "test"
Requires-Dist: types-PyYAML>=5.1 ; extra == "test"
Requires-Dist: ruff ; extra == "test"
Requires-Dist: bandit ; extra == "test"
Project-URL: Documentation, https://pyfirecrest.readthedocs.io
Project-URL: Homepage, https://pyfirecrest.readthedocs.io
Project-URL: Repository, https://github.com/eth-cscs/pyfirecrest
Provides-Extra: dev
Provides-Extra: docs
Provides-Extra: test
